robot_simulator/__init__.py
robot_simulator/__main__.py
robot_simulator/run.py
robot_simulator/core/__init__.py
robot_simulator/core/commands.py
robot_simulator/core/constants.py
robot_simulator/core/decoder.py
robot_simulator/core/encoder.py
robot_simulator/core/logger_manager.py
robot_simulator/core/responses.py
robot_simulator/core/responses_manager.py
robot_simulator/core/robot_simulator_server.py
robot_simulator/core/settings.py
robot_simulator/core/settings_manager.py
robot_simulator/core/utils.py
robot_simulator-1.0.0.dev1.dist-info/LICENCE
robot_simulator-1.0.0.dev1.dist-info/METADATA
robot_simulator-1.0.0.dev1.dist-info/WHEEL
robot_simulator-1.0.0.dev1.dist-info/entry_points.txt
robot_simulator-1.0.0.dev1.dist-info/top_level.txt
robot_simulator-1.0.0.dev1.dist-info/RECORD
