Metadata-Version: 2.2
Name: robot_simulator
Version: 1.0.0.dev1
Summary: Simulator robot
Author-email: LupinDental <contact@lupindental.com>
Maintainer-email: LupinDental <contact@lupindental.com>
Project-URL: Repository, https://gitlab.com/lupindental/arsene/software/simulators/robot_simulator
Classifier: Programming Language :: Python :: 3.10
Classifier: Programming Language :: Python :: 3.11
Classifier: Programming Language :: Python :: 3.12
Classifier: Development Status :: 3 - Alpha
Requires-Python: >=3.10
License-File: LICENCE
Requires-Dist: typer==0.15.2
Provides-Extra: dev
Requires-Dist: coverage; extra == "dev"
Requires-Dist: pytest; extra == "dev"
Requires-Dist: pytest-asyncio; extra == "dev"
Requires-Dist: pytest-cov; extra == "dev"
